LICENSE
README.md
setup.py
Nebula_web.egg-info/PKG-INFO
Nebula_web.egg-info/SOURCES.txt
Nebula_web.egg-info/dependency_links.txt
Nebula_web.egg-info/entry_points.txt
Nebula_web.egg-info/requires.txt
Nebula_web.egg-info/top_level.txt
nebula/__init__.py
nebula/commands.py
nebula/fields.py
nebula/manage.py
nebula/models.py
nebula/server.py
nebula/utils.py
nebula/project_template/manage.py
nebula/project_template/project_name/__init__.py
nebula/project_template/project_name/models.py
nebula/project_template/project_name/settings.py
nebula/project_template/project_name/urls.py
nebula/project_template/project_name/views.py